{"10139":{"id":10139,"name":"Team Chess Battle 2024","currentRound":{"id":103884,"slug":"03-02","groupId":8948,"startAt":"2024-03-08T21:10:15.553Z"},"imageUrl":"https://images.chesscomfiles.com/uploads/v1/event/f317cfc6-c9c7-11ee-8057-e7dee83bd619.a072fb59.250x250o.b4e678e1f81d.png","slug":"2024-team-chess-battle","startAt":"2024-02-22T00:00:00+00:00","endAt":"2024-03-09T05:55:00+00:00","eventType":"knockout","playerCount":8,"roundCount":7,"streams":[{"startAt":"2024-02-21T17:50:00+00:00","endAt":"2024-02-21T20:05:00+00:00","type":"twitch","channel":"Chess","language":{"id":10,"nameNative":"English","locale":"en_US"},"title":"Anish/Danny v Fabiano/Cristian! Who'll Win The War of Chess But More Importantly War of Words? Team Chess Battle 2024 Quarterfinals 1"},{"startAt":"2024-02-22T16:45:00+00:00","endAt":"2024-02-22T19:05:00+00:00","type":"twitch","channel":"Chess","language":{"id":10,"nameNative":"English","locale":"en_US"},"title":"Wesley So/Alice Lee vs. Peter Leko/Pia Cramling! Will The Younger Pros Take Down The Legends? | Team Chess Battle Quarterfinals 2"},{"startAt":"2024-02-26T19:45:00+00:00","endAt":"2024-02-26T22:30:00+00:00","type":"twitch","channel":"Chess","language":{"id":10,"nameNative":"English","locale":"en_US"},"title":"Naroditsky/Hess vs. Svidler/Gustafsson! Who'll Win The Most Awaited Battle Of Commentators? Team Chess Battle 2024 Quarterfinals #3"},{"startAt":"2024-02-27T18:45:00+00:00","endAt":"2024-02-27T21:30:00+00:00","type":"twitch","channel":"Chess","language":{"id":10,"nameNative":"English","locale":"en_US"},"title":"Hikaru \u0026 GothamChess Join Hands vs. Chessbrah Eric Hansen \u0026 Van Foreest! Will The Chess Streamers Win At Banter? Team Chess Battle 2024 QF 4"},{"startAt":"2024-03-01T18:00:00+00:00","endAt":"2024-03-01T20:30:00+00:00","type":"twitch","channel":"Chess","language":{"id":10,"nameNative":"English","locale":"en_US"},"title":"Team Chess Battle SF1 - Caruana/Chirila vs So/Lee"},{"startAt":"2024-03-05T19:00:00+00:00","endAt":"2024-03-05T21:55:00+00:00","type":"twitch","channel":"Chess","language":{"id":10,"nameNative":"English","locale":"en_US"},"title":"Hikaru/GothamChess v Hess/Naroditsky! Batman \u0026 Robin Of Chess Face-off vs. The Commentator Duo! Team Chess Battle 2024 Semifinal 2"},{"startAt":"2024-03-08T20:00:00+00:00","endAt":"2024-03-08T22:30:00+00:00","type":"twitch","channel":"Chess","language":{"id":10,"nameNative":"English","locale":"en_US"},"title":"FINAL: Fabiano/Cristian v. Naroditsky/Hess! Will Podcasters Sink The Commentators In A David v. Goliath Match? TEAM CHESS BATTLE 2024"}],"weight":83,"type":"event","isFeatured":false,"mainV2ImageUrl":"https://images.chesscomfiles.com/uploads/v1/event/f317cfc6-c9c7-11ee-8057-e7dee83bd619-2.65827dcb.320x180o.32063638c79b.png","bannerImageUrl":"https://images.chesscomfiles.com/uploads/v1/event/f317cfc6-c9c7-11ee-8057-e7dee83bd619-1.8d203668.728x410o.6f0feaf83bce.png","featuredTitle":"Watch The Finals On March 8 at 3 p.m. ET / 21:00 CET!","uuid":"d4bfa981-69fb-595d-8315-52004654e616","updatedAt":"2024-03-11T00:13:27.394Z"},"9852":{"id":9852,"name":"Titled Cup 2024","imageUrl":"https://images.chesscomfiles.com/uploads/v1/event_index/eb71fed8-a3cd-11ee-8b81-0b949b4ec240.24b12108.250x250o.1bd51b29e0a3.png","slug":"2024-titled-cup","startAt":"2024-01-02T00:00:00+00:00","endAt":"2024-12-31T22:00:00+00:00","eventType":"","playerCount":18913,"roundCount":0,"weight":79,"type":"index","isFeatured":true,"mainV2ImageUrl":"https://images.chesscomfiles.com/uploads/v1/event_index/eb71fed8-a3cd-11ee-8b81-0b949b4ec240-1.f5f00aa5.320x180o.ac77a7cdbf94.png","bannerImageUrl":"https://images.chesscomfiles.com/uploads/v1/event_index/eb71fed8-a3cd-11ee-8b81-0b949b4ec240-2.bc1a741d.728x410o.a2048df2cd9a.jpg","featuredTitle":"Titled (Tuesday) Cup 2024 - Watch Titled Tuesdays at 11 a.m. and 5 p.m. ET / 17:00 and 23:00 CET!","uuid":"9cf5ced6-3014-5d25-afdb-b448d666c0f0","updatedAt":"2024-04-18T00:13:45.119Z"},"9746":{"id":9746,"name":"Collegiate Chess League: Spring 2024","imageUrl":"https://images.chesscomfiles.com/uploads/v1/event_index/100ad08a-9474-11ee-9666-f31a2c2cbef8.8615429b.250x250o.b282b01adb37.png","slug":"2024-collegiate-chess-league-spring","startAt":"2024-01-20T19:00:00+00:00","endAt":"2024-04-07T16:55:00+00:00","eventType":"","playerCount":80,"roundCount":0,"weight":78,"type":"index","isFeatured":true,"mainV2ImageUrl":"https://images.chesscomfiles.com/uploads/v1/event_index/100ad08a-9474-11ee-9666-f31a2c2cbef8-1.e8f24848.320x180o.b444272d2371.png","bannerImageUrl":"https://images.chesscomfiles.com/uploads/v1/event_index/100ad08a-9474-11ee-9666-f31a2c2cbef8-2.484300b6.728x410o.a03e9e4529a6.png","featuredTitle":"Watch The CCL Saturdays at 2 p.m. ET / 19:00 CET!","uuid":"e771ad1d-442a-5dee-9cf5-32941890e99a","updatedAt":"2024-03-25T00:14:12.418Z"},"9263":{"id":9263,"name":"German Chess Bundesliga 2023-2024","currentRound":{"slug":"15"},"imageUrl":"","slug":"2023-2024-german-chess-bundesliga","startAt":"2023-10-21T12:00:00+00:00","endAt":"2024-04-28T21:55:00+00:00","eventType":"team-round-robin","playerCount":234,"roundCount":15,"streams":[{"startAt":"2024-03-16T13:00:00+00:00","endAt":"2024-03-16T23:00:00+00:00","type":"youtube","channel":"QcSKZDqSEHA","language":{"id":10,"nameNative":"English","locale":"en_US"},"title":"Kommentierung der Vierheimer Partien mit GM Ilja Zaragatski"},{"startAt":"2024-03-17T09:00:00+00:00","endAt":"2024-03-17T19:00:00+00:00","type":"youtube","channel":"dcL1rwnTfuA","language":{"id":10,"nameNative":"English","locale":"en_US"},"title":"Kommentierung der Vierheimer Partien mit GM Ilja Zaragatski"}],"weight":65,"type":"event","isFeatured":true,"mainV2ImageUrl":"https://images.chesscomfiles.com/uploads/v1/event/9724b422-654f-11ee-b1ee-ff4da81a6bbf-2.c97dc7a2.320x180o.ead1b9cf79f7.png","bannerImageUrl":"","featuredTitle":"","uuid":"8724cc24-60e8-5c98-9bac-3677ce2ef1a6","updatedAt":"2024-04-07T00:15:38.808Z"},"9368":{"id":9368,"name":"German Women's Chess Bundesliga 2023/2024","currentRound":{"slug":"11"},"imageUrl":"","slug":"2023-2024-german-womens-chess-bundesliga","startAt":"2023-10-14T12:00:00+00:00","endAt":"2024-06-09T21:55:00+00:00","eventType":"team-round-robin","playerCount":121,"roundCount":11,"streams":[],"weight":60,"type":"event","isFeatured":true,"mainV2ImageUrl":"https://images.chesscomfiles.com/uploads/v1/event/333511fa-6a09-11ee-8ece-b31bed393668-2.deddab3c.320x180o.9a2f6bb4016e.png","bannerImageUrl":"","featuredTitle":"","uuid":"d0a6e6d8-09d8-58f5-bf53-6928c651f3cb","updatedAt":"2024-02-28T19:00:16.092Z"},"10109":{"id":10109,"name":"Prague International Chess Festival 2024","imageUrl":"https://images.chesscomfiles.com/uploads/v1/event_index/27708436-c67e-11ee-a09f-a1921bc7fafd.07eaf38c.250x250o.c0f2cba6fc0b.png","slug":"2024-prague-chess-festival","startAt":"2024-02-27T14:00:00+00:00","endAt":"2024-03-07T22:55:00+00:00","eventType":"","playerCount":299,"roundCount":0,"weight":81,"type":"index","isFeatured":true,"mainV2ImageUrl":"https://images.chesscomfiles.com/uploads/v1/event_index/27708436-c67e-11ee-a09f-a1921bc7fafd-1.956df416.320x180o.a03846fa9984.png","bannerImageUrl":"https://images.chesscomfiles.com/uploads/v1/event_index/27708436-c67e-11ee-a09f-a1921bc7fafd-2.7f1246bf.728x410o.bf1b8a835171.png","featuredTitle":"","uuid":"f8075fd6-5eb4-574b-9820-d698c5609d08","updatedAt":"2024-03-07T00:10:52.196Z"},"10271":{"id":10271,"name":"Shenzhen Longgang Chess Masters 2024","currentRound":{"id":103266,"slug":"04","groupId":9052,"startAt":"2024-03-04T12:00:00.000Z"},"imageUrl":"","slug":"2024-shenzhen-longgang-chess-masters","startAt":"2024-02-29T07:00:00+00:00","endAt":"2024-03-07T15:55:00+00:00","eventType":"round-robin","playerCount":8,"roundCount":7,"streams":[],"weight":79,"type":"event","isFeatured":true,"mainV2ImageUrl":"https://images.chesscomfiles.com/uploads/v1/event/23233ede-d649-11ee-991e-9f3d49b8d55b-2.89ec5646.320x180o.2996d27bf07e.png","bannerImageUrl":"https://images.chesscomfiles.com/uploads/v1/event/23233ede-d649-11ee-991e-9f3d49b8d55b-1.3277e0e4.728x410o.89a826144b7b.png","featuredTitle":"","uuid":"69d2ae68-681e-5bf7-b7c4-83f81b6b3477","updatedAt":"2024-03-08T00:13:38.663Z"},"10266":{"id":10266,"name":"The American Cup 2024","imageUrl":"https://images.chesscomfiles.com/uploads/v1/event_index/e2786eae-d599-11ee-9061-5d1bef8b3b2b.8ff7d05d.250x250o.cc111f8e400d.png","slug":"2024-the-american-cup","startAt":"2024-03-12T19:00:00+00:00","endAt":"2024-03-22T18:55:00+00:00","eventType":"","playerCount":56,"roundCount":0,"weight":82,"type":"index","isFeatured":true,"mainV2ImageUrl":"https://images.chesscomfiles.com/uploads/v1/event_index/e2786eae-d599-11ee-9061-5d1bef8b3b2b-1.a54db718.320x180o.13454b3f122e.png","bannerImageUrl":"https://images.chesscomfiles.com/uploads/v1/event_index/e2786eae-d599-11ee-9061-5d1bef8b3b2b-2.33d8ba6e.728x410o.98f5abb35bf7.png","featuredTitle":"","uuid":"f69c4e61-47ce-5e58-bf04-93f164f5711b","updatedAt":"2024-03-22T00:13:11.708Z"},"10262":{"id":10262,"name":"BlitzChamps: Maryland","imageUrl":"https://images.chesscomfiles.com/uploads/v1/event_index/1e17b854-d589-11ee-871d-bd272f0935f8.93c20562.250x250o.9391d56b0354.png","slug":"2024-blitzchamps-maryland","startAt":"2024-03-13T19:30:00+00:00","endAt":"2024-03-14T05:55:00+00:00","eventType":"","playerCount":12,"roundCount":0,"weight":80,"type":"index","isFeatured":true,"mainV2ImageUrl":"https://images.chesscomfiles.com/uploads/v1/event_index/1e17b854-d589-11ee-871d-bd272f0935f8-1.39bba229.320x180o.e935952f653d.png","bannerImageUrl":"https://images.chesscomfiles.com/uploads/v1/event_index/1e17b854-d589-11ee-871d-bd272f0935f8-2.a9abc1e1.728x410o.583753e14f4a.png","featuredTitle":"","uuid":"16eddfe5-613a-54fa-bbdc-796f911d9fc4","updatedAt":"2024-03-14T00:13:06.107Z"},"10298":{"id":10298,"name":"Champions Chess Tour 2024","imageUrl":"https://images.chesscomfiles.com/uploads/v1/event/efd4051e-da3e-11ee-bda9-9f44fc85b824.e4df69f1.250x250o.83c41adc4c7a.png","slug":"2024-champions-chess-tour","startAt":"2024-01-01T05:00:00+00:00","endAt":"2025-01-01T16:55:00+00:00","eventType":"swiss","playerCount":0,"roundCount":0,"streams":[],"weight":70,"type":"event","isFeatured":true,"mainV2ImageUrl":"https://images.chesscomfiles.com/uploads/v1/event/efd4051e-da3e-11ee-bda9-9f44fc85b824-2.5bffebd3.320x180o.4044154e9889.jpg","bannerImageUrl":"https://images.chesscomfiles.com/uploads/v1/event/efd4051e-da3e-11ee-bda9-9f44fc85b824-1.e0fc42c2.728x410o.cb639577b517.jpg","featuredTitle":"","uuid":"3768e3e2-d540-5a51-a5c4-c307a878e628","updatedAt":"2024-03-14T00:13:06.107Z"},"9922":{"id":9922,"name":"Reykjavik Open 2024","currentRound":{"id":100193,"slug":"04","groupId":8770,"startAt":"2024-03-17T13:00:00.000Z"},"imageUrl":"https://images.chesscomfiles.com/uploads/v1/event/2ee721fc-abfd-11ee-8cba-8931c566fd08.d5f55b2c.250x250o.95ac968b7d5b.png","slug":"2024-reykjavik-open","startAt":"2024-03-15T15:00:00+00:00","endAt":"2024-03-21T23:55:00+00:00","eventType":"swiss","playerCount":402,"roundCount":9,"streams":[{"startAt":"2024-03-15T15:00:00+00:00","endAt":"2024-03-15T19:30:00+00:00","type":"youtube","channel":"5PH2VVJ5Zng","language":{"id":10,"nameNative":"English","locale":"en_US"},"title":"Reykjavik Open Coverage"}],"weight":78,"type":"event","isFeatured":true,"mainV2ImageUrl":"https://images.chesscomfiles.com/uploads/v1/event/2ee721fc-abfd-11ee-8cba-8931c566fd08-2.f60a424d.320x180o.41fa2c114d79.png","bannerImageUrl":"https://images.chesscomfiles.com/uploads/v1/event/2ee721fc-abfd-11ee-8cba-8931c566fd08-1.d986024a.728x410o.8ab64770afdd.png","featuredTitle":"","uuid":"3bea34d3-9200-5f77-b63b-d67aa9981649","updatedAt":"2024-03-20T00:12:51.543Z"},"10382":{"id":10382,"name":"GRENKE Chess Classic and Open 2024","imageUrl":"https://images.chesscomfiles.com/uploads/v1/event_index/a0cccb44-e60b-11ee-b393-675aac3c54c9.b829e237.250x250o.7596bb4a370a.png","slug":"2024-grenke-chess-classic-and-open","startAt":"2024-03-26T14:00:00+00:00","endAt":"2024-04-01T21:55:00+00:00","eventType":"","playerCount":962,"roundCount":0,"weight":87,"type":"index","isFeatured":true,"mainV2ImageUrl":"https://images.chesscomfiles.com/uploads/v1/event_index/a0cccb44-e60b-11ee-b393-675aac3c54c9-1.83aa4631.320x180o.e8c76a337724.png","bannerImageUrl":"https://images.chesscomfiles.com/uploads/v1/event_index/a0cccb44-e60b-11ee-b393-675aac3c54c9-2.729a01d0.728x410o.722b316cdd3f.png","featuredTitle":"","uuid":"de022c3a-4a3a-5447-ad4a-43a95d1fbcbe","updatedAt":"2024-04-02T00:13:30.430Z"},"10046":{"id":10046,"name":"FIDE Candidates Chess Tournaments 2024","imageUrl":"https://images.chesscomfiles.com/uploads/v1/event_index/4c14347c-bb6b-11ee-92c7-25c8bc987339.4ad4bdfd.250x250o.e894449189a4.png","slug":"2024-fide-candidates-chess-tournaments","startAt":"2024-04-04T19:00:00+00:00","endAt":"2024-04-23T15:55:00+00:00","eventType":"","playerCount":16,"roundCount":0,"weight":95,"type":"index","isFeatured":true,"mainV2ImageUrl":"https://images.chesscomfiles.com/uploads/v1/event_index/4c14347c-bb6b-11ee-92c7-25c8bc987339-1.ccf5ca76.320x180o.fa3e7b45f49e.png","bannerImageUrl":"https://images.chesscomfiles.com/uploads/v1/event_index/4c14347c-bb6b-11ee-92c7-25c8bc987339-2.67dec8dc.728x410o.93a7d1c0640b.png","featuredTitle":"The Candidates and Women's Candidates Begin At 2:30 p.m. ET / 20:30 CEST!","uuid":"49f75a26-d6fe-56a7-9174-0f4b6414afcb","updatedAt":"2024-04-05T00:13:43.949Z"},"10471":{"id":10471,"name":"Menorca Open 2024","currentRound":{"id":105128,"slug":"08","groupId":9216,"startAt":"2024-04-06T15:00:00.000Z"},"imageUrl":"","slug":"2024-menorca-open","startAt":"2024-04-02T16:00:00+00:00","endAt":"2024-04-07T21:55:00+00:00","eventType":"swiss","playerCount":286,"roundCount":9,"streams":[{"startAt":"2024-04-02T07:00:00+00:00","endAt":"2024-04-03T00:00:00+00:00","type":"youtube","channel":"WyWMIRBZ9Pc","language":{"id":10,"nameNative":"English","locale":"en_US"},"title":"Menorca Chess Open"},{"startAt":"2024-04-02T07:00:00+00:00","endAt":"2024-04-03T00:00:00+00:00","type":"youtube","channel":"ASITSDBoHlI","language":{"id":11,"nameNative":"Español","locale":"es_ES"},"title":"Menorca Chess Open"},{"startAt":"2024-04-02T07:00:00+00:00","endAt":"2024-04-03T00:00:00+00:00","type":"youtube","channel":"ASITSDBoHlI","language":{"id":11,"nameNative":"Español","locale":"es_ES"},"title":"Menorca Chess Open"},{"startAt":"2024-04-03T07:00:00+00:00","endAt":"2024-04-03T13:00:00+00:00","type":"youtube","channel":"KrRnBaXPI9Q","language":{"id":11,"nameNative":"Español","locale":"es_ES"},"title":"Menorca Chess Open"},{"startAt":"2024-04-03T15:00:00+00:00","endAt":"2024-04-03T19:00:00+00:00","type":"youtube","channel":"pJAkYF-LxNI","language":{"id":11,"nameNative":"Español","locale":"es_ES"},"title":"Menorca"},{"startAt":"2024-04-04T07:00:00+00:00","endAt":"2024-04-04T15:00:00+00:00","type":"youtube","channel":"kH5194cUo4w","language":{"id":11,"nameNative":"Español","locale":"es_ES"},"title":"Menorca"},{"startAt":"2024-04-04T07:00:00+00:00","endAt":"2024-04-04T14:00:00+00:00","type":"youtube","channel":"GCnJt_4A-mw","language":{"id":10,"nameNative":"English","locale":"en_US"},"title":"Menorca"},{"startAt":"2024-04-04T14:10:00+00:00","endAt":"2024-04-04T19:00:00+00:00","type":"youtube","channel":"hah2TMd2Mlg","language":{"id":10,"nameNative":"English","locale":"en_US"},"title":"Menorca"},{"startAt":"2024-04-04T14:30:00+00:00","endAt":"2024-04-04T19:00:00+00:00","type":"youtube","channel":"lAy3AZm0rIE","language":{"id":11,"nameNative":"Español","locale":"es_ES"},"title":"Menorca"},{"startAt":"2024-04-05T07:00:00+00:00","endAt":"2024-04-05T21:00:00+00:00","type":"youtube","channel":"4NU0L81faao","language":{"id":11,"nameNative":"Español","locale":"es_ES"},"title":"Menorca"},{"startAt":"2024-04-06T07:00:00+00:00","endAt":"2024-04-06T14:00:00+00:00","type":"youtube","channel":"QdeslLWCUdk","language":{"id":11,"nameNative":"Español","locale":"es_ES"},"title":"Menorca Chess Open"},{"startAt":"2024-04-06T07:00:00+00:00","endAt":"2024-04-06T14:00:00+00:00","type":"youtube","channel":"ZaECDCh-2vw","language":{"id":10,"nameNative":"English","locale":"en_US"},"title":"Menorca Open"},{"startAt":"2024-04-06T15:00:00+00:00","endAt":"2024-04-06T21:00:00+00:00","type":"youtube","channel":"PbICqbWsIH0","language":{"id":11,"nameNative":"Español","locale":"es_ES"},"title":"Menorca"},{"startAt":"2024-04-06T15:00:00+00:00","endAt":"2024-04-06T22:00:00+00:00","type":"youtube","channel":"eImhbpLheq4","language":{"id":10,"nameNative":"English","locale":"en_US"},"title":"Menorca"}],"weight":80,"type":"event","isFeatured":true,"mainV2ImageUrl":"https://images.chesscomfiles.com/uploads/v1/event/3f0af442-ee82-11ee-b847-71ee7a483b1f-2.2497231e.320x180o.788f0ae56571.png","bannerImageUrl":"","featuredTitle":"","uuid":"9c56f6f8-ff4e-5440-9feb-1f90d78b0a64","updatedAt":"2024-04-07T00:15:38.808Z"},"10507":{"id":10507,"name":"Sunway Formentera Chess Festival 2024","currentRound":{"id":105398,"slug":"09","groupId":9246,"startAt":"2024-04-17T22:00:00.000Z"},"imageUrl":"https://images.chesscomfiles.com/uploads/v1/event/301bbefc-f51d-11ee-82a3-918190a619c5.d790df0a.250x250o.35d8b392af2a.jpg","slug":"2024-sunway-formentera-chess-festival","startAt":"2024-04-09T13:00:00+00:00","endAt":"2024-04-19T21:55:00+00:00","eventType":"swiss","playerCount":52,"roundCount":10,"streams":[{"startAt":"2024-04-17T13:00:00+00:00","endAt":"2024-04-17T18:00:00+00:00","type":"twitch","channel":"botezlive","language":{"id":10,"nameNative":"English","locale":"en_US"},"title":"Sunway Formentera Chess Festival"},{"startAt":"2024-04-18T13:00:00+00:00","endAt":"2024-04-18T18:00:00+00:00","type":"twitch","channel":"botezlive","language":{"id":10,"nameNative":"English","locale":"en_US"},"title":"Sunway Formentera Chess Festival"}],"weight":76,"type":"event","isFeatured":true,"mainV2ImageUrl":"https://images.chesscomfiles.com/uploads/v1/event/301bbefc-f51d-11ee-82a3-918190a619c5-2.b6df4a96.320x180o.143b527c39dc.jpg","bannerImageUrl":"","featuredTitle":"","uuid":"9e5bb4b2-bfde-5317-8a9f-e1cdc91798e3","updatedAt":"2024-04-19T00:13:52.739Z"},"10429":{"id":10429,"name":"Spring Chess Classic 2024","imageUrl":"https://images.chesscomfiles.com/uploads/v1/event_index/b99fcf9e-eb7f-11ee-b9ad-47b3cb0f4a3b.839c0846.250x250o.56f4e6cbe815.png","slug":"2024-spring-chess-classic","startAt":"2024-04-11T18:00:00+00:00","endAt":"2024-04-20T04:55:00+00:00","eventType":"","playerCount":20,"roundCount":0,"weight":80,"type":"index","isFeatured":true,"mainV2ImageUrl":"https://images.chesscomfiles.com/uploads/v1/event_index/b99fcf9e-eb7f-11ee-b9ad-47b3cb0f4a3b-1.26365398.320x180o.80114c2ae8c4.png","bannerImageUrl":"https://images.chesscomfiles.com/uploads/v1/event_index/b99fcf9e-eb7f-11ee-b9ad-47b3cb0f4a3b-2.7b70ef1b.728x410o.aec3e1b827de.png","featuredTitle":"","uuid":"1bc7f74e-76aa-57f0-9c70-3999a42539fc","updatedAt":"2024-04-12T00:13:28.209Z"}}